kingpin/__init__.py
kingpin/alias.py
kingpin/draw.py
kingpin/kingpin.py
kingpin/model.py
kingpin/plot.py
kingpin/prior.py
kingpin/proposal.py
kingpin/recorder.py
kingpin/rjmcmc.py
kingpin/stack.py
kingpin/tgp.py
kingpin/tree.py
kingpin_tgp-1.0.0.dist-info/LICENSE
kingpin_tgp-1.0.0.dist-info/METADATA
kingpin_tgp-1.0.0.dist-info/WHEEL
kingpin_tgp-1.0.0.dist-info/entry_points.txt
kingpin_tgp-1.0.0.dist-info/top_level.txt
kingpin_tgp-1.0.0.dist-info/RECORD
