Metadata-Version: 2.1
Name: kingpin-tgp
Version: 1.0.0
Summary: Treed Gaussian Process
Home-page: https://github.com/andrewfowlie/kingpin
Author: Andrew Fowlie
Author-email: Andrew Fowlie <andrew.fowlie@xjtlu.edu.cn>
License: MIT License
Project-URL: Bug Tracker, https://github.com/andrewfowlie/kingpin/issues
Classifier: Programming Language :: Python :: 3
Classifier: License :: OSI Approved :: MIT License
Classifier: Operating System :: OS Independent
Requires-Python: >=3.6
License-File: LICENSE
Requires-Dist: arviz
Requires-Dist: binarytree
Requires-Dist: celerite2
Requires-Dist: click
Requires-Dist: ezcurses
Requires-Dist: joblib
Requires-Dist: matplotlib
Requires-Dist: numpy
Requires-Dist: scipy
Requires-Dist: tqdm
